fontawesome/__init__.py
fontawesome/resource.py
fontawesomeicons-2.0.0.dist-info/METADATA
fontawesomeicons-2.0.0.dist-info/WHEEL
fontawesomeicons-2.0.0.dist-info/RECORD
